{"OUTPUT": {"TL431": {"Vka": ["+ V(1)", "+ V(3)"], "Vref": ["+ V(1)", "+ V(2)"], "Iref": ["+ V(1)", "+ I(Viref)"], "PreRad": ["+ V(1)", "+ V(2)", "+ V(3)", "+ I(Vika)", "+ I(Viref)", "+ V(X1:REF)"], "Ika": ["+ V(1)", "+ I(Vika)"]}, "LT1175": {"Line Regualtion": ["+ V(4)", "+ V(1)"]}, "AD590": {"Default": ["+ V(2)", "+ I(VOUT)"]}}, "FUNCTIONS": {"LT1175": ["*DeltaIb = 1*(exp(a2+(b2*Veb)+(c2*(Veb*Veb))) - exp(a1+(b1*Veb)+(c1*(Veb*Veb))))", "*.func deltaIb(x) {scale*(exp(a2+(b2*x)+(c2*(pow(x,2)))) - exp(a1+(b1*x)+(c1*(pow(x,2)))))}", ".func deltaIb1(x) {scale1*(exp(a2+(b2*x)+(c2*(x*x))) - exp(a1+(b1*x)+(c1*(x*x))))}", ".func deltaIb2(x) {scale2*(exp(a2+(b2*x)+(c2*(x*x))) - exp(a1+(b1*x)+(c1*(x*x))))}", ".func deltaIb3(x) {scale3*(exp(a2+(b2*x)+(c2*(x*x))) - exp(a1+(b1*x)+(c1*(x*x))))}", ".func deltaIb4(x) {scale4*(exp(a2+(b2*x)+(c2*(x*x))) - exp(a1+(b1*x)+(c1*(x*x))))}", "", ".func deltaIb6(x) {scale6*(exp(a2+(b2*x)+(c2*(x*x))) - exp(a1+(b1*x)+(c1*(x*x))))}", ".func deltaIb7(x) {scale7*(exp(a2+(b2*x)+(c2*(x*x))) - exp(a1+(b1*x)+(c1*(x*x))))}", ".func deltaIb8(x) {scale8*(exp(a2+(b2*x)+(c2*(x*x))) - exp(a1+(b1*x)+(c1*(x*x))))}", ".func deltaIb9(x) {scale9*(exp(a2+(b2*x)+(c2*(x*x))) - exp(a1+(b1*x)+(c1*(x*x))))}", ".func deltaIb10(x) {scale10*(exp(a2+(b2*x)+(c2*(x*x))) - exp(a1+(b1*x)+(c1*(x*x))))}"], "AD590": ["*DeltaIb = 1*(exp(a2+(b2*Veb)+(c2*(Veb*Veb))) - exp(a1+(b1*Veb)+(c1*(Veb*Veb))))", "*.func deltaIb(x) {scale*(exp(a2+(b2*x)+(c2*(pow(x,2)))) - exp(a1+(b1*x)+(c1*(pow(x,2)))))}", "*PNP", ".func deltaIb1(x) {scale1*((exp(a2+(b2*x)+(c2*(x*x)))) - (exp(a1+(b1*x)+(c1*(x*x)))))}", ".func deltaIb2(x) {scale2*((exp(a2+(b2*x)+(c2*(x*x)))) - (exp(a1+(b1*x)+(c1*(x*x)))))}", ".func deltaIb3(x) {scale3*((exp(a2+(b2*x)+(c2*(x*x)))) - (exp(a1+(b1*x)+(c1*(x*x)))))}", ".func deltaIb4(x) {scale4*((exp(a2+(b2*x)+(c2*(x*x)))) - (exp(a1+(b1*x)+(c1*(x*x)))))}", ".func deltaIb5(x) {scale5*((exp(a2+(b2*x)+(c2*(x*x)))) - (exp(a1+(b1*x)+(c1*(x*x)))))}", ".func deltaIb6(x) {scale6*((exp(a2+(b2*x)+(c2*(x*x)))) - (exp(a1+(b1*x)+(c1*(x*x)))))}", "", "*NPN", ".func deltaIb7(x) {scale7*((exp(a4+(b4*x)+(c4*(x*x)))) - (exp(a3+(b3*x)+(c3*(x*x)))))}", ".func deltaIb8(x) {scale8*((exp(a4+(b4*x)+(c4*(x*x)))) - (exp(a3+(b3*x)+(c3*(x*x)))))}", ".func deltaIb9(x) {scale9*((exp(a4+(b4*x)+(c4*(x*x)))) - (exp(a3+(b3*x)+(c3*(x*x)))))}", ".func deltaIb10(x) {scale10*((exp(a4+(b4*x)+(c4*(x*x)))) - (exp(a3+(b3*x)+(c3*(x*x)))))}", ".func deltaIb11(x) {scale11*((exp(a4+(b4*x)+(c4*(x*x)))) - (exp(a3+(b3*x)+(c3*(x*x)))))}"]}, "OUTPUT_OPTION": {"TL431": ["+ V(1)", "+ V(2)"], "LT1175": ["+ V(4)", "+ V(1)"], "AD590": ["+ V(2)", "+ I(VOUT)"]}, "INPUT": {"TL431": [".dc V1 10 25 0.1"], "LT1175": [".dc V2 0 -20 -0.1"], "AD590": [".dc VIN 0 30 0.01"]}, "INPUT_VOLTAGE_SOURCE": {"TL431": ["V1 1 0 DC 0V"], "LT1175": ["V2 4 0 DC 0V"], "AD590": ["VIN 2 0 DC 0V", "VOUT 20 0 0"]}, "CIRCUIT_CORE": {"TL431": ["*Subcircuit", "*X1 REF K A", "X1 2 3 0 TL431_sc", "", "*Resistance: R<name> <+ node> <- node> [model name] <value>", "r21 4 0 6800", "r22 5 4 10000", "r23 5 1 180", "", "Vika 5 3 0", "Viref 4 2 0"], "LT1175": ["*Subcircuit", "*X1 VCC VEE VREF", "X1 0 4 5 BG_sc", "", "*X4 V+ V- VCC VEE VO", "X4 6 5 0 4 7 OPAMP_sc", "", "*Resistance: R<name> <+ node> <- node> [model name] <value>", "r1 0 6 350k", "r2 6 1 100k", "rLIM 3 4 0.001", "", "*BJT: Q<name> <collector> <base> <emitter> [substrate] <model name> [area value]", "Q1 1 2 3 QNMOD 1000", "Q2 0 7 2 QNMOD 10"], "AD590": ["XZ 2 20 AD590", "R0 20 0 1m"]}, "LIBRARY_TID_LEVEL_MODEL": {"300k": ["* npn 3e5 off ctp 3b", ".model QNMOD NPN (", "+ IS     = 1.684E-16", "+ BF     = 38.7            NF     = 0.986787        VAF    = 329.7773204", "+ IKF    = 0.0251189       NK     = 0.47574         ISE    = 2.089296E-12", "+ NE     = 1.871           BR     = 0.697           NR     = 2", "+ VAR    = 100             IKR    = 0.1             ISC    = 1E-17", "+ NC     = 2               RB     = 170.83          IRB    = 1E-3", "+ RBM    = 50              RE     = 2               RC     = 366.4     )", "", "* lpnp 3e5 off ctp 3b", ".model QLPMOD PNP (", "+ IS     = 1E-15", "+ BF     = 33              NF     = 0.99            VAF    = 33.1203665", "+ IKF    = 1.09648E-4      NK     = 0.37            ISE    = 3.801894E-13", "+ NE     = 1.44            BR     = 0.697           NR     = 2", "+ VAR    = 100             IKR    = 0.1             ISC    = 1E-17", "+ NC     = 2               RB     = 1.58489E3       IRB    = 3.16228E-5", "+ RBM    = 57.544          RE     = 7.093           RC     = 1               )"], "50k": ["* npn 5e4 off ctp 3b", ".model QNMOD NPN  (", "+ IS     = 1.684E-16", "+ BF     = 38.7            NF     = 0.986787        VAF    = 342.7968454", "+ IKF    = 0.0251189       NK     = 0.47574         ISE    = 1.41254E-13", "+ NE     = 1.82            BR     = 0.697           NR     = 2", "+ VAR    = 100             IKR    = 0.1             ISC    = 1E-17", "+ NC     = 2               RB     = 170.83          IRB    = 1E-3", "+ RBM    = 50              RE     = 2               RC     = 366.4)", "", "* lpnp 5e4 off ctp 3b", ".model QLPMOD PNP (", "+ IS     = 1E-15", "+ BF     = 47.4            NF     = 0.99            VAF    = 34.9777903", "+ IKF    = 1.09648E-4      NK     = 0.37            ISE    = 1.65959E-13", "+ NE     = 1.44            BR     = 0.697           NR     = 2", "+ VAR    = 100             IKR    = 0.1             ISC    = 1E-17", "+ NC     = 2               RB     = 1.90546E3       IRB    = 3.16228E-5", "+ RBM    = 57.544          RE     = 7.093           RC     = 1)"], "20k": ["* npn 2e4 off ctp 3b", ".model QNMOD NPN  (                      ", "+ IS     = 1.68208E-16", "+ BF     = 45.95           NF     = 0.986787        VAF    = 345.2016293", "+ IKF    = 0.0229087       NK     = 0.47574         ISE    = 1.122018E-14", "+ NE     = 1.65            BR     = 0.697           NR     = 2", "+ VAR    = 100             IKR    = 0.1             ISC    = 1E-17", "+ NC     = 2               RB     = 140.86          IRB    = 1E-3", "+ RBM    = 50              RE     = 2               RC     = 250.75)", "", "* lpnp 2e4 off ctp 3b", ".model QLPMOD PNP (", "+ IS     = 8.70964E-16", "+ BF     = 264.9           NF     = 0.99            VAF    = 35.8970174", "+ IKF    = 9.549926E-5     NK     = 0.52            ISE    = 5.495409E-14", "+ NE     = 1.42            BR     = 0.697           NR     = 2", "+ VAR    = 100             IKR    = 0.1             ISC    = 1E-17", "+ NC     = 2               RB     = 1E3             IRB    = 3.6E-5", "+ RBM    = 100             RE     = 4.096           RC     = 1)"], "pre_rad": ["* npn prerad off ctp 3b", ".model QNMOD NPN (", "+ IS = 1.68208E-16", "+ BF = 84.058    NF = 0.986787 VAF = 351.9861415", "+ IKF = 9.86E-3  NK = 0.47574  ISE = 7.1029E-15", "+ NE = 2.06453   BR = 0.697    NR = 2", "+ VAR = 100      IKR = 0.1     ISC = 1E-17", "+ NC = 2         RB = 140.86   IRB = 1E-3", "+ RBM = 50       RE = 2        RC = 250.75)", "", "*lpnp prerad off ctp 3b", ".model QLPMOD PNP (", "+ IS = 8.70964E-16", "+ BF = 786.9\t\tNF = 0.99                           VAF = 36.3423711", "+ IKF = 6.30957E-5       NK = 0.52                           ISE = 9.54993E-17", "+ NE = 1.27089           BR = 0.697                          NR = 2", "+ VAR = 100              IKR = 0.1                           ISC = 1E-17", "+ NC = 2                 RB = 758.578                        IRB = 3.6E-5", "+ RBM = 100              RE = 4.096                           RC = 1)"], "200k": ["* npn 2e5 off ctp 3b", ".model QNMOD NPN  (", "+ IS     = 1.684E-16", "+ BF     = 38.7            NF     = 0.986787        VAF    = 313.65875", "+ IKF    = 0.0251189       NK     = 0.47574         ISE    = 1.28825E-12", "+ NE     = 1.854           BR     = 0.697           NR     = 2", "+ VAR    = 100             IKR    = 0.1             ISC    = 1E-17", "+ NC     = 2               RB     = 170.83          IRB    = 1E-3", "+ RBM    = 50              RE     = 2               RC     = 366.4)", "", "* lpnp 2e5 off ctp 3b", ".model QLPMOD PNP (", "+ IS     = 1E-15", "+ BF     = 38.7            NF     = 0.99            VAF    = 32.8110824", "+ IKF    = 1.09648E-4      NK     = 0.37            ISE    = 3.31131E-13", "+ NE     = 1.44            BR     = 0.697           NR     = 2", "+ VAR    = 100             IKR    = 0.1             ISC    = 1E-17", "+ NC     = 2               RB     = 1.58489E3       IRB    = 3.16228E-5", "+ RBM    = 57.544          RE     = 7.093           RC     = 1)"], "100k": ["* npn 1e5 off ctp 3b", ".model QNMOD NPN  (", "+ IS     = 1.68208E-16", "+ BF     = 45.95           NF     = 0.986787        VAF    = 342.3319825", "+ IKF    = 0.0229087       NK     = 0.47574         ISE    = 2.238721E-13", "+ NE     = 1.701           BR     = 0.697           NR     = 2", "+ VAR    = 100             IKR    = 0.1             ISC    = 1E-17", "+ NC     = 2               RB     = 140.86          IRB    = 1E-3", "+ RBM    = 50              RE     = 2               RC     = 250.75)", "* lpnp 1e5 off ctp 3b", ".model QLPMOD PNP (", "+ IS     = 1E-15", "+ BF     = 47.4            NF     = 0.99            VAF    = 33.7331598", "+ IKF    = 1.09648E-4      NK     = 0.37            ISE    = 2.884032E-13", "+ NE     = 1.44            BR     = 0.697           NR     = 2", "+ VAR    = 100             IKR    = 0.1             ISC    = 1E-17", "+ NC     = 2               RB     = 1.737801E3      IRB    = 3.16228E-5", "+ RBM    = 57.544          RE     = 7.093           RC     = 1               )"]}, "SCALE": {"LT1175": ["*SCALE", ".PARAM scale1=1", ".PARAM scale2=1", ".PARAM scale3=1", ".PARAM scale4=0.1", "", ".PARAM scale6=20", ".PARAM scale7=20", ".PARAM scale8=1", ".PARAM scale9=10", ".PARAM scale10=10"], "AD590": ["*SCALE", ".PARAM scale1=10", ".PARAM scale2=10", ".PARAM scale3=10", ".PARAM scale4=10", ".PARAM scale5=10", ".PARAM scale6=10", ".PARAM scale7=10", ".PARAM scale8=10", ".PARAM scale9=280", ".PARAM scale10=35", ".PARAM scale11=35"]}, "LIBRARY_JFET": {"TL431": [], "LT1175": [], "AD590": ["", "*JFET", ".model NJF_TYP NJF (", "+ VTO = -1.0\tBETA = 6.2E-4\tLAMBDA = 0.003", "+ RD = 0.01      RS = 1e-4", "+ CGS = 3E-12    CGD=1.5E-12     IS=5E-10)", ""]}, "SUBCIRCUIT": {"TL431": {"model": [".subckt TL431_sc REF K A ", "*Capacitance: C<name> <+ node> <- node> [model name] <value> + [IC=<initial value>]", "C1 5 3 20p", "C2 16 K 20p", "", "*Resistance: R<name> <+ node> <- node> [model name] <value>", "R1 K 13 180", "R20 K 12 180", "R2 6 5 1100", "R5 4 3 2400", "R4 4 1 2400", "R3 7 4 2500", "R8 19 A 4800", "R9 19 18 33", "R7 8 1 270", "R6 9 A 373", "", "*BJT: Q<name> <collector> <base> <emitter> [substrate] <model name> [area value]", "Q2 K REF 7 QNMOD 2", "Q3 16 16 REF QNMOD 3", "Q4 11 11 12 QLPMOD 2", "Q5 16 11 13 QLPMOD 1", "Q6 11 7 6 QNMOD 1", "Q7 3 1 9 QNMOD 7.2", "Q8 1 1 A QNMOD 0.9", "Q9 5 3 A QNMOD 1", "Q10 16 8 A QNMOD 1", "Q11 K 16 18 QNMOD 2.5", "Q12 K 19 A QNMOD 50", "", "*ends of the TL431_sc subcircuit", ".ends"]}, "LT1175": {"model": [".subckt BG_sc VCC VEE VREF", "*Resistance: R<name> <+ node> <- node> [model name] <value>", "r1 VCC 1 10k", "r2 1 8 2.93e6", "r3 8 9 109k", "r4 4 VEE 600", "r5 6 VEE 600", "", "*BJT: Q<name> <collector> <base> <emitter> [substrate] <model name> [area value]", "Q1 2 2 VCC QLPMOD 1", "Q2 3 2 1 QLPMOD 1", "Q3 12 5 9 QLPMOD 1", "Q4 11 5 8 QLPMOD 0.1", "Q5 12 12 7 QNMOD 1", "Q6 11 12 7 QNMOD 1", "Q7 VCC 5 7 QNMOD 1", "Q8 3 3 4 QNMOD 1", "Q9 7 3 6 QNMOD 1", "", "*Voltage Controlled Voltage Source: E<name> <+ node> <-node> <+ controlling node> <- controlling node> <gain>", "E1 VCC VREF VCC 5 1", "", "*Independent Current Source: I<name> <+ node> <-node> [[DC] <value>]", "I1 2 0 DC 3.23uA", "", "*end of the BG_sc subcircuit", ".ends BG_sc", "", ".subckt OPAMP_sc V10 V11 VCC VEE VO", "*Resistance: R<name> <+ node> <- node> [model name] <value>", "r1 7 VEE 4.7k", "r2 3 VEE 4.7k", "r3 VO VEE 60k", "r4 11 VEE 60k", "", "*Capacitance: C<name> <+ node> <- node> [model name] <value> + [IC=<initial value>]", "C1 1 9 0.0056p", "", "*BJT: Q<name> <collector> <base> <emitter> [substrate] <model name> [area value]", "Q1 1 11 VEE QNMOD 10", "Q2 VCC 1 VO QNMOD 1", "Q3 VCC 9 11 QNMOD 1", "Q4 9 4 7 QNMOD 1", "Q5 4 4 3 QNMOD 1", "Q6 9 V10 5 QLPMOD 20", "Q7 4 V11 5 QLPMOD 20", "Q8 6 6 VCC QLPMOD 1", "Q9 5 6 VCC QLPMOD 10", "Q10 1 6 VCC QLPMOD 10", "", "*Independent Current Source: I<name> <+ node> <-node> [[DC] <value>]", "I1 6 0 DC 1.4u", "", "*end of the OPAMP_sc subcircuit", ".ends OPAMP_sc"], "source": [".subckt BG_sc VCC VEE VREF", "*Voltage Controlled Current Source BG", "B1 VCC 2 I={deltaIb1(V(VCC)-V(2))}", "B2 1 2 I={deltaIb2(V(1)-V(2))}", "B3 9 5 I={deltaIb3(V(9)-V(5))}", "B4 8 5 I={deltaIb4(V(8)-V(5))}", "", "*Resistance: R<name> <+ node> <- node> [model name] <value>", "r1 VCC 1 10k", "r2 1 8 2.93e6", "r3 8 9 109k", "r4 4 VEE 600", "r5 6 VEE 600", "", "*BJT: Q<name> <collector> <base> <emitter> [substrate] <model name> [area value]", "Q1 2 2 VCC QLPMOD 1", "Q2 3 2 1 QLPMOD 1", "Q3 12 5 9 QLPMOD 1", "Q4 11 5 8 QLPMOD 0.1", "Q5 12 12 7 QNMOD 1", "Q6 11 12 7 QNMOD 1", "Q7 VCC 5 7 QNMOD 1", "Q8 3 3 4 QNMOD 1", "Q9 7 3 6 QNMOD 1", "", "*Voltage Controlled Voltage Source: E<name> <+ node> <-node> <+ controlling node> <- controlling node> <gain>", "E1 VCC VREF VCC 5 1", "", "*Independent Current Source: I<name> <+ node> <-node> [[DC] <value>]", "I1 2 0 DC 3.23uA", "", "*end of the BG_sc subcircuit", ".ends BG_sc", "", "", ".subckt OPAMP_sc V10 V11 VCC VEE VO", "", "*Voltage Controlled Current Source OPAMP", "B6 5 V10 I={deltaIb6(V(5)-V(V10))}", "B7 5 V11 I={deltaIb7(V(5)-V(V11))}", "B8 6 VCC I={deltaIb8(V(6)-V(VCC))}", "B9 6 VCC I={deltaIb9(V(6)-V(VCC))}", "B10 6 VCC I={deltaIb10(V(6)-V(VCC))}", "", "*Resistance: R<name> <+ node> <- node> [model name] <value>", "r1 7 VEE 4.7k", "r2 3 VEE 4.7k", "r3 VO VEE 60k", "r4 11 VEE 60k", "", "*Capacitance: C<name> <+ node> <- node> [model name] <value> + [IC=<initial value>]", "C1 1 9 0.0056p", "", "*BJT: Q<name> <collector> <base> <emitter> [substrate] <model name> [area value]", "Q1 1 11 VEE QNMOD 10", "Q2 VCC 1 VO QNMOD 1", "Q3 VCC 9 11 QNMOD 1", "Q4 9 4 7 QNMOD 1", "Q5 4 4 3 QNMOD 1", "Q6 9 V10 5 QLPMOD 20", "Q7 4 V11 5 QLPMOD 20", "Q8 6 6 VCC QLPMOD 1", "Q9 5 6 VCC QLPMOD 10", "Q10 1 6 VCC QLPMOD 10", "", "*Independent Current Source: I<name> <+ node> <-node> [[DC] <value>]", "I1 6 0 DC 1.4u", "", "*end of the OPAMP_sc subcircuit", ".ends OPAMP_sc"]}, "AD590": {"model": [".subckt AD590 2 20", "", "*Capacitance: C<name> <+ node> <- node> [model name] <value> + [IC=<initial value>]", "c1 1 8 26p", "", "*Resistance: R<name> <+ node> <- node> [model name] <value>", "r1 2 4 260", "r2 2 3 1040", "r3 5 16 5000", "r4 11 5 11000", "r5 12 20 146", "r6 15 20 820", "", "*BJT: Q<name> <collector> <base> <emitter> [substrate] <model name> [area value]", "Q11 1 5 12 QNMOD 35 temp=27", "Q10 5 5 12 QNMOD 35 temp=27", "Q9 6 5 15 QNMOD 280 temp=27", "Q6 7 7 2 QLPMOD 10 temp=27", "Q4 1 8 4 QLPMOD 10 temp=27", "Q3 1 8 4 QLPMOD 10 temp=27", "Q5 8 8 3 QLPMOD 10 temp=27", "Q2 6 8 4 QLPMOD 10 temp=27", "Q1 6 8 4 QLPMOD 10 temp=27", "Q7 7 6 11 QNMOD 10 temp=27", "Q8 8 1 11 QNMOD 10 temp=27", "", "*JFET: J<name> <drain> <gate> <source> <model name> [area value]", "J1 8 16 11 NJF_TYP", "", "*end of the subcircuit", ".ends"], "source": [".subckt AD590 2 20", "", "*Voltage Controlled Current Source", "*PNP", "B1 4 8 I={deltaIb1(V(4)-V(8))}", "B2 4 8 I={deltaIb2(V(4)-V(8))}", "B3 4 8 I={deltaIb3(V(4)-V(8))}", "B4 4 8 I={deltaIb4(V(4)-V(8))}", "B5 3 8 I={deltaIb5(V(3)-V(8))}", "B6 2 7 I={deltaIb6(V(2)-V(7))}", "*NPN", "B7 6 11 I={deltaIb7(V(6,11))}", "B8 1 11 I={deltaIb8(V(1,11))}", "B9 5 15 I={deltaIb9(V(5,15))}", "B10 5 12 I={deltaIb10(V(5,12))}", "B11 5 12 I={deltaIb11(V(5,12))}", "", "*Capacitance: C<name> <+ node> <- node> [model name] <value> + [IC=<initial value>]", "c1 1 8 26p", "", "*Resistance: R<name> <+ node> <- node> [model name] <value>", "r1 2 4 260", "r2 2 3 1040", "r3 5 16 5000", "r4 11 5 11000", "r5 12 20 146", "r6 15 20 820", "", "*BJT: Q<name> <collector> <base> <emitter> [substrate] <model name> [area value]", "Q11 1 5 12 QNMOD 35 temp=27", "Q10 5 5 12 QNMOD 35 temp=27", "Q9 6 5 15 QNMOD 280 temp=27", "Q6 7 7 2 QLPMOD 10 temp=27", "Q4 1 8 4 QLPMOD 10 temp=27", "Q3 1 8 4 QLPMOD 10 temp=27", "Q5 8 8 3 QLPMOD 10 temp=27", "Q2 6 8 4 QLPMOD 10 temp=27", "Q1 6 8 4 QLPMOD 10 temp=27", "Q7 7 6 11 QNMOD 10 temp=27", "Q8 8 1 11 QNMOD 10 temp=27", "", "*JFET: J<name> <drain> <gate> <source> <model name> [area value]", "J1 8 16 11 NJF_TYP", "", "*end of the subcircuit", ".ends"]}}}